{"frames": [

{
	"filename": "001.png",
	"frame": {"x":0,"y":0,"w":32,"h":32},
	"rotated": false,
	"trimmed": false,
	"spriteSourceSize": {"x":0,"y":0,"w":32,"h":32},
	"sourceSize": {"w":32,"h":32},
	"pivot": {"x":0.5,"y":0.5}
},
{
	"filename": "002.png",
	"frame": {"x":32,"y":0,"w":32,"h":32},
	"rotated": false,
	"trimmed": false,
	"spriteSourceSize": {"x":0,"y":0,"w":32,"h":32},
	"sourceSize": {"w":32,"h":32},
	"pivot": {"x":0.5,"y":0.5}
},
{
	"filename": "003.png",
	"frame": {"x":64,"y":0,"w":32,"h":32},
	"rotated": false,
	"trimmed": false,
	"spriteSourceSize": {"x":0,"y":0,"w":32,"h":32},
	"sourceSize": {"w":32,"h":32},
	"pivot": {"x":0.5,"y":0.5}
},
{
	"filename": "004.png",
	"frame": {"x":0,"y":32,"w":32,"h":32},
	"rotated": false,
	"trimmed": false,
	"spriteSourceSize": {"x":0,"y":0,"w":32,"h":32},
	"sourceSize": {"w":32,"h":32},
	"pivot": {"x":0.5,"y":0.5}
},
{
	"filename": "005.png",
	"frame": {"x":32,"y":32,"w":32,"h":32},
	"rotated": false,
	"trimmed": false,
	"spriteSourceSize": {"x":0,"y":0,"w":32,"h":32},
	"sourceSize": {"w":32,"h":32},
	"pivot": {"x":0.5,"y":0.5}
},
{
	"filename": "006.png",
	"frame": {"x":64,"y":32,"w":32,"h":32},
	"rotated": false,
	"trimmed": false,
	"spriteSourceSize": {"x":0,"y":0,"w":32,"h":32},
	"sourceSize": {"w":32,"h":32},
	"pivot": {"x":0.5,"y":0.5}
},
{
	"filename": "007.png",
	"frame": {"x":0,"y":64,"w":32,"h":32},
	"rotated": false,
	"trimmed": false,
	"spriteSourceSize": {"x":0,"y":0,"w":32,"h":32},
	"sourceSize": {"w":32,"h":32},
	"pivot": {"x":0.5,"y":0.5}
},
{
	"filename": "008.png",
	"frame": {"x":32,"y":64,"w":32,"h":32},
	"rotated": false,
	"trimmed": false,
	"spriteSourceSize": {"x":0,"y":0,"w":32,"h":32},
	"sourceSize": {"w":32,"h":32},
	"pivot": {"x":0.5,"y":0.5}
},
{
	"filename": "009.png",
	"frame": {"x":64,"y":64,"w":32,"h":32},
	"rotated": false,
	"trimmed": false,
	"spriteSourceSize": {"x":0,"y":0,"w":32,"h":32},
	"sourceSize": {"w":32,"h":32},
	"pivot": {"x":0.5,"y":0.5}
}],
"meta": {
	"app": "http://www.codeandweb.com/texturepacker",
	"version": "1.0",
	"image": "qingmingjiaoyin.png",
	"format": "RGBA8888",
	"size": {"w":96,"h":96},
	"scale": "1",
	"smartupdate": "$TexturePacker:SmartUpdate:cb08a2c2abcd6a2a1fdd9ee268980148:07254e879507c43b282c561850598aff:53f9fbc0f66555adc541848b8027645f$"
}
}
